<?xml version="1.0" encoding="utf-8"?>
<base xmlns:xsi="http://www.w3.org/2001/XMLSchema-instance" xmlns:xsd="http://www.w3.org/2001/XMLSchema" type="string">
	<tags>
		<tag language="简体中文"/>
	</tags>
	<strings>
		<!-- bandit factions -->
  		<string id="eHpYLY0J" text="法外狂徒"/>
  		<string id="3YedNR4h" text="帝国逃兵"/>
  		<string id="PKogKXLA" text="混沌信徒"/>
  		<string id="peksS4WD" text="劣角兽战帮"/>
  		<string id="dwbMyOTs" text="诺斯卡劫掠者"/>
  		<string id="FC8kwb4r" text="巴托尼亚法外狂徒"/>
		
		 <!-- Averland faction -->
  		<string id="q835xYhK" text="莱特多夫"/>
  		<string id="ozKpEhXB" text="莱特多夫家族是艾维兰地区历史悠久的贵族世家，如今，马吕斯・莱特多夫是艾维兰的选帝侯伯爵。尽管这一身份代表着该地区的最高权力，但莱特多夫家族面临着来自阿尔普特劳姆家族的反对，后者仍不遗余力地在艾维兰争夺权力。"/>
  		<string id="tC7WRtY0" text="阿尔普特劳姆"/>
  		<string id="gysrNTAm" text="阿尔普特劳姆家族是一个有权有势的家族，在莱特多夫家族发动政变夺权之前，他们一直掌控着艾维兰。自那以后，阿尔普特劳姆家族就一直试图重夺艾维兰的控制权，他们认为莱特多夫家族正在把当地的经济和政府搞得一团糟。"/>
  		<string id="D5ZtT3ky" text="艾维兰协定"/>
  		<string id="jGcv7RIY" text="莱特多夫家族与阿尔普特劳姆家族之间的政治斗争复杂程度令人难以置信。和其他更文明的国家不同，对艾维兰来说，速战速决的简单战争远远不够，反而是琐碎的政治手段更受重视。就在这时，《艾维兰协定》应运而生。当其他领主在阿尔普特劳姆家族和莱特多夫家族之间摇摆不定时，参与协定的领主们联合起来，以各自的方式保障彼此的安全。 "/>
  		<string id="4SQ6EaYq" text="焰阳骑士团"/>
  		<string id="hOCOUS7a" text="焰阳骑士团是一小支精锐的圣殿骑士团体，他们全身心投入到战争科学与艺术的研习与精通之中。这些米尔米迪亚（战争女神）的狂热追随者，将能力与成就看得比包括贵族出身在内的所有其他因素都更为重要。正因如此，这个骑士团日益兴盛，吸引了最杰出的军事人才投身其麾下。一名焰阳骑士骑士的首要目标，是在战争艺术上臻于完美。所以，他们独自穿梭于旧世界，四处寻觅大大小小的战斗。有焰阳骑士骑士领军的战帮是一股强大力量，他们对付敌人时足智多谋，往往在战斗正式打响前，就已稳操胜券。 "/>
  		<string id="jxtxfKRO" text="黄金学院"/>
  		<string id="X1ZwccjA" text="黄金学院是帝国中训练巫师的八大学院之一。黄金巫师是金属、矿石和炼金术（他们称之为“炼金术奇术”）的大师。在旧世界的所有人中，他们在这个领域是最有技巧的。因此，黄金巫师倾向于将这些物质熔炼成难以驾驭的液体，以增强他们的魔力。该学院在阿尔道夫（Altdorf）的总部大体上是一个巨大的锻造工坊，到处是烟囱和熔炉。它的位置靠近瑞克河（River Reik），以便冷却熔炉。他们所研习的魔法知识是金属系魔法。"/>

		<!-- Sylvania faction -->
  		<string id="tC7WRtY0" text="冯·卡斯坦因"/>
  		<string id="wF0SbRkf" text="人们说，历史是由伟大的男男女女铸就的。对于吸血鬼而言，这话千真万确，不过，还没有哪个家族书写历史时，能像冯·卡斯坦因家族这般大胆无畏、血腥浓稠。他们是暗夜的贵族，满怀炽热情感与无尽野心，就连他们最微不足道的欲望，都能左右整个国家的命运。在所有受诅咒的血脉中，他们最为强大，这邪恶的族裔，源自远古的恐惧——弗拉德·冯·卡斯坦因伯爵。数百年来，他们向生者发动战争，弗拉德的子嗣永远玷污着大地，让土地被鲜血浸透。大约四百年前，西尔凡尼亚的最后一位伟大伯爵，曼弗雷德·冯·卡斯坦因，在海尔芬恩之战中被杀。如今，他卷土重来，要夺回曾经理直气壮属于他的一切。 "/>
  		<string id="Oa09hbO5" text="梦魇血统"/>
  		<string id="XUq2cVGG" text="甚至在弗拉德·冯·卡斯坦因和他那些嗜血的子嗣降临之前，西尔凡尼亚就已是一片被诅咒的土地，被帝国厌恶，视作死灵法师与巫师的避风港。许多这类黑暗术士本就是统治着不安坟墓的领主和贵族，他们研习禁忌之术，以求取权力与永生。自冯·卡斯坦因家族掌权后的数个世纪以来，凡世的贵族与吸血鬼贵族形成了一种共生关系，双方共同确保西尔凡尼亚永远掌控在那些执掌纳加什之力的人手中。尽管吸血鬼伯爵们起起落落，但那些贵族依旧留存，他们是强大的死灵法师，永远追寻着纳加什的智慧。 "/>
  		<string id="kvr1fW6s" text="叛徒之血"/>
  		<string id="nqrU7oMu" text="第三次吸血鬼战争结束，严酷的戈特利布展开清洗行动之后，西尔凡尼亚地区在法理上被并入了斯提尔兰大公国。即便如此，这片土地依旧是个永远被诅咒、遭人嫌恶的地方，稍有见识的贵族都鲜少涉足。于是，它成了一处流放之地，那些败家子、落魄贵族在斯提尔兰宫廷中没了容身之所后，便被打发到这里继承产业。这些被放逐者中，许多人以坚毅的决心承担起新职责，另一些人则谋求更大机遇。正是这些叛徒、弑亲者与骗子，为了受诅咒的命运背叛了自己的家园与家族。他们是最年轻的一批吸血鬼，新生的“婴儿”，却有着恶魔般的力量与贪欲。他们唯一的渴望，便是沉醉于新生的不死之身，为自己黑暗的本性而狂喜，在瑟瑟发抖的凡人中间，如神祇般生活。 "/>
  		<string id="LpboDqNY" text="猩红教团"/>
  		<string id="DK29umZP" text="在第三次吸血鬼战争期间，据说曼弗雷德·冯·卡斯坦因在山间偶然发现了一座孤塔，他向远方的血亲——阿博拉什的血龙家族求助，期望借他们之力征服西格玛帝国。不管他许下了怎样的诺言，血龙家族还是与西尔凡尼亚亲王并肩进军，他们是武艺无双的勇猛战士，出于荣誉宣誓效忠于冯·卡斯坦因的大业。尽管那场战争结束，曼弗雷德也战死了，但仍有部分血龙家族成员留了下来，他们因曾效力于此，理所当然地占据了西尔凡尼亚的土地。作为西尔凡尼亚唯一值得一提的其他吸血鬼血脉，血龙家族已然闯出了赫赫凶名，他们是无可匹敌的战士，只向那些他们认为值得的对象宣誓效忠。当曼弗雷德再度归来时，他再次让血龙家族履行誓言，于是血龙们又一次奔赴战场。 "/>

		<!-- Blood Dragons faction -->
  		<string id="bxKNaxgm" text="血龙骑士团"/>
  		<string id="HB6CWonm" text="血堡曾是一支英勇骑士团——血龙骑士团（又称奥多·德拉科尼斯）的驻地。在一个宿命之夜，一位名叫瓦拉赫·哈肯的吸血鬼向每位骑士发起一对一决斗挑战，最终将他认为有价值的骑士全部转化为吸血鬼。血龙骑士团覆灭之后，又在鲜血中重生；从那时起，这些令人胆寒的战士就被称为血龙。帝国军民在他们的攻击与劫掠下苦熬了六十年，才集结起一支大军将血堡夷为平地。那差不多是六个世纪之前的事了，此后漫长岁月里，血堡的废墟一直无人惊扰。如今，血堡再度拔地而起，由沉默的不死者建造而成，帝国的子民将再度陷入恐惧。 "/>
  		<string id="stfnBSlA" text="暗影之塔"/>
  		<string id="2xp9rkDm" text="扎卡里亚斯致力于钻研《死灵魔法书》，他和追随者们在他的高塔中积聚力量，意图摧毁帝国及其盟友。扎卡里亚斯从帝国各地招募追随者，以扩充他的军队。在杀死他那位古老的黑暗导师梅尔基奥尔之后，他成了现存最强大的死灵法师。"/>
  		<string id="iu0tcKPc" text="兰布鲁克疯人院余部"/>
  		<string id="Y8KUOLiE" text="兰布鲁克疯人院原本是一个医师公会，它不像莎莉雅（医疗女神）的女祭司们在收容所里做的那样，为精神错乱者提供救助，而是作为一个在偏僻之地研究疯子的场所，只有野兽和树木才会听到那些凄厉的惨叫。兰布鲁克疯人院由费德医生和蒂尔医生经营，他们处于行业前沿，采用诸如颅骨钻孔术（在头骨上打孔，把作祟的恶魔放出去）、甲状腺摘除术、烙铁烫以及轻度投毒这类颇具前瞻性的手段。在登托马兹杀死工作人员后，他便将那些疯子收为己用，成了他的仆人。  "/>

		<!-- Stirland faction -->
  		<string id="jOpUzR8Y" text="豪普特 - 安德森"/>
  		<string id="jw1e3gV6" text="阿尔贝里希·豪普特 - 安德森初掌大权时，竭尽全力在所有其他领主之间缔结紧密联盟，以保障乌尔茨巴赫及施蒂尔兰西部的经济稳定与安全。即便在形势最为有利的时候，由于阿尔贝里希年纪尚轻，加之其家族地位普遍不稳，维持这一联盟也绝非易事。随着与希尔瓦尼亚接壤的东部边境局势愈发紧张，这个联盟正变得越来越摇摇欲坠。 "/>
  		<string id="fp5VbEj3" text="莫尔信徒"/>
  		<string id="pIQeq22l" text="施蒂尔兰西部的领主们乐于为与木精族领地（the Moot）和艾维兰的贸易事务争吵不休，而东部的领主们却十分清楚边境上正在酝酿的麻烦。死者不得安息，庄稼歉收，越来越多的不祥之兆从西尔凡尼亚地区传出。他们已经有好几个月没能与那块土地上的领主取得联系了，如今，向东的道路太过危险，根本没法尝试通行。不过，预兆不会说谎；东部的领主们眼睁睁看着曾经肥沃的土地，因腐败而变得暗沉，他们的顾问魔法师称，这种腐败来自更遥远的东方。结果，他们放弃了任何求和的念头，为战争或者更糟的情况做好了准备。穿行在施蒂尔兰的这片区域，也会给人同样的印象：这些是帝国的边境居民，是抵御邪恶的第一道防线，并且愿意正面迎击邪恶。 "/>
  		<string id="txyRYRl7" text="南斯提尔领"/>
  		<string id="fQuzuyS6" text="南斯提尔领是斯卡拉诺拉克朝圣路线的所在地，这条路线从施拉姆布莱本一直延伸到南部山区。虽说它让这片地区声名远扬，还能让西格玛教会助力抵御不死者的腐化，但施蒂尔兰南部也存在不少问题，像是外来者和朝圣者从正规商店行窃、半身人边境争端，以及有人企图在用于斯卡拉诺拉克朝圣的朱夫巴尔道路上伏击朝圣者。 "/>
  		<string id="erqxZnh1" text="西格玛教会"/>
  		<string id="SPfaWfy4" text="西格玛教会是帝国的国教，负责主持对帝国守护神明——持锤者西格玛的崇拜仪式。如今，西格玛教会已然成为帝国社会不可或缺的一部分。帝国几乎每一座城市、城镇或村庄，都拿出一部分财富与土地，用于建造及维护一座西格玛神庙，西格玛教会的牧师便从这些神庙出发，关怀市民的精神福祉，方式或是神圣的祈祷词，或是英勇的行动与战斗试炼。出于对他们的战神的狂热虔诚，西格玛教会的牧师要求信徒凭借自身的力量与信仰，去对抗已知世界中的各类邪恶。帝国军队开拔作战时，教会的众多牧师也会随军出征。这种正义感、自主意识，以及来自一位严厉却仁慈的神明的庇佑，确保了帝国的子民成为一个信仰坚定、意志顽强、精神不可战胜的群体。 "/>

		<!-- Wissenland faction -->
  		<string id="DQRjhKG2" text="冯·利布维茨"/>
  		<string id="xRVmwqEY" text="冯·利布维茨家族是一个相对新兴的家族，在过去的一个世纪才崛起，掌控了努恩及其周边紧邻地区。伊曼纽尔和利奥斯的父亲曾是上一任选帝侯伯爵；由于他突然离世，而利奥斯年纪又太小，无法继承王位，伊曼纽尔便成了威森兰的选帝侯女伯爵。 "/>
  		<string id="K8zST2dQ" text="托彭海默"/>
  		<string id="Jpa635OV" text="托彭海默家族是一个备受尊崇的家族，他们统治着威森领南部与索兰北部至少五个世纪之久。他们与封臣及臣民之间的关系颇为有趣，因为托彭海默家族常被视作既不完全属于威森领，也不完全属于索尔领。这种特殊关系让他们得以在威森兰扮演“造王者”的角色，无论谁得到他们的青睐，都会比省内省外的对手拥有巨大优势。 "/>
  		<string id="SPfcnIuy" text="索尔"/>
  		<string id="MQe9WtDZ" text="索尔曾经充满希望与光明。如今，人们的灵魂背负着沉重的耻辱，一种倦怠感好似将先辈们所承受的痛苦，统统压在了他们身上。自从几个世纪前被绿皮兽人摧毁后，索尔就再也没能恢复元气，相应地，这里的民众曾经乐观积极的精神也变得忧郁消沉。该地区的领主们也没什么不同。他们竭尽所能减轻子民的负担，同时时刻准备应对下一个黎明可能带来的任何变故。 "/>

		<!-- Talabecland faction -->
  		<string id="VkZvjUnw" text="塔尔天选者"/>
  		<string id="BU452U5a" text="塔尔天选者是塔拉贝克领的统治家族。这个家族由两个家族联合而成：塔拉贝姆的统治者伊莉丝女伯爵家族，以及塔拉贝克兰大公国的统治者赫尔穆特·费尔巴哈大公家族。两大家族深知，塔尔的子民为争夺圣地控制权而争斗实属愚蠢之举，于是，这场政治联姻巩固了双方的联盟。如今，这个王朝已进入第二代统治者时期；古斯塔夫十一世·克里格利茨 - 安特恩将女儿伊莉丝嫁给赫尔穆特，从而促成了这一联盟。作为选帝侯伯爵，赫尔穆特是家族与塔拉贝克兰的官方统治者，以铁腕手段和暴躁脾气闻名。不过，据传伊莉丝女伯爵在省内真正的政治决策过程中参与度更高，她在塔尔与维雷娜的教会中颇具影响力。 "/>
  		<string id="9LgpHBH3" text="格伦茨瓦赫特"/>
  		<string id="mueQqEgn" text="这是一个低调的家族，有着尚武的背景。他们独善其身，用自己的方式解决内部问题。他们对陌生人或难民并不友好。 "/>
  		<string id="lXMmB0Zv" text="林登豪特"/>
  		<string id="YXBhiMsG" text="林登豪特家族将势力集中在斯特尔河沿岸以及塔拉贝克领南部的荒野地区。他们是塔尔的虔诚崇拜者，家族中的许多成员经常会同塔尔教会的守护者，诸如长脚族和德鲁伊们一起，致力于让大森林免受玷污。冯·席拉赫家族之外的贵族常常抱怨他们冷漠又举止粗鲁；很多时候，由于他们频繁踏上穿越塔尔圣地的漫长朝圣之旅，外界很难与某些家族成员取得联系。 "/>

		<!-- Reikland faction -->
  		<string id="6I5ve28c" text="冯·霍尔斯维格·施利斯坦"/>
  		<string id="JYaZQU9z" text="冯·霍尔斯维格·施利斯坦家族是人类帝国的统治王朝。其家族首领是皇帝卡尔-弗朗茨·冯·霍尔斯维格·施利斯坦。该家族由智者威廉皇帝创立，他于帝国历2429年至2434年统治帝国。如今，冯·霍尔施维格 - 施利施泰因家族在阿尔道夫根基稳固，他们的纹章极为常见，以至于常被错认成这座城市自身的标志。 "/>
  		<string id="wx0ZpaAb" text="冯·华伦斯坦"/>
  		<string id="fyRbK34J" text=""/>
		<string id="o0Z8EXex" text="冯·马肯森"/>
  		<string id="L3WsYQ31" text=""/>
  		<string id="wdZTOqm6" text="冯·萨波纳特海姆"/>
  		<string id="011VaHOK" text=""/>

		<!-- Middenland faction -->
  		<string id="rq3qhnVS" text="托德布林格"/>
  		<string id="9ikap43v" text="托德布林格家族源自古老的条顿国王一脉，他们曾统治如今帝国的北部地区。南北之间由来已久的对立一直延续至今，敌对状态时而通过外交手段爆发，时而诉诸武力。托德布林格家族支持设立皇帝这一需求，鲍里斯自认为是皇位的完美人选，而非西格玛教会的傀儡。然而，德拉克瓦尔德森林以及利爪海带来的诸多威胁，让这位选帝侯伯爵疲于应对，无暇他顾。 "/>
  		<string id="EfMHUKyj" text="冯·比尔德霍芬"/>
  		<string id="L1yHapun" text="尽管冯·比尔德霍芬家族离瑞克领很近，但这并不能改变他们与帝国北方土地更为亲近的事实。比尔德霍芬家族拥有历史悠久的血脉，可一直追溯到虔诚者马格努斯·冯·比尔德霍芬。然而，即便有着如此辉煌的家族传承，比尔德霍芬家族如今所剩的影响力也不多了，这个贵族家族处于一种平和却无足轻重的地位。 "/>
  		<string id="aicVoaMs" text="德拉科瓦尔德守卫"/>
  		<string id="AwWldMQr" text="德拉科瓦尔德守卫因抗击日益增长的野兽人威胁、保护黑暗森林各处众多商队与村庄的需求应运而生。该组织的军队成员来自那些曾经存在、后被消灭或打散的男爵领地、猎人和雇佣兵。不过，乌尔里克的虔诚追随者也会协助他们作战。他们以乌尔里克与托德布林格家族之名，清除德拉克瓦尔德森林所遭受的混沌污染。 "/>

		<!-- Ostermark faction -->
  		<string id="EG7YVme0" text="赫特威格"/>
  		<string id="q2mRaaKB" text="1485年，15岁的沃尔夫拉姆·赫特威格在一场兽人 waaagh! 入侵之后，临危受命成为奥斯特马克的首相，填补权力空缺。在黑路之战中，年轻的沃尔夫拉姆拒绝让经验更为丰富的永耀骑士团大团长率领奥斯特马克的军队对抗兽人。结果，毫无经验的他带领部下遭遇惨败，这场败仗臭名昭著，被称作“赫特维格的愚蠢之举” 。如今，沃尔夫拉姆和赫特维格家族大体上已经重塑了自家声誉，因为许多奥斯特马克人记得，在“赫特维格的愚蠢之举”发生后，他们展现出的领导力，以及此后本省取得的成功。然而在外地人眼中，赫特维格家族依旧因那位年轻伯爵以及一场本可取胜却遭遇失败的战役而被人记起。 "/>
  		<string id="JDDAS9pE" text="施韦斯布劳"/>
  		<string id="xINeQm79" text="施魏斯布劳家族并非出身贵族血统，但专注与决心足以成为替代品。斯特凡·胡塞尔本是平民出身，是当地乡村铁匠的儿子。他所在的村子遭到一群四处游荡、寻觅软柿子捏的野兽人的袭击，村民们仓惶逃窜，却很快被屠戮殆尽，他的父亲也没能幸免，就在被一只昂戈尔兽兵刺穿之前，斯特凡与父亲对视了最后一眼。斯特凡抄起自己锻造的一把利刃，无视那些奔逃的村民，那一刻，他内心发生了变化。他回身反击野兽，斩杀那些企图攻击他的昂戈尔与戈尔兽兵。一些正在奔逃的当地人回头，回忆起看到他置身于黑暗与血泊之中，周身却包裹着一层耀眼光芒，毫发无损地向前突进。村民们受到鼓舞，操起干草叉与木槌，转身冲向野兽人。当斯特凡拎着率队袭击村子的野兽领主那滴血的头颅时，野兽人溃败而逃。从那天起，普通民众意识到，他们不需要华丽的铠甲或精良的武器，仅凭决心与勇气就能击退人类的敌人。周边村庄渐渐认可斯特凡做他们的领袖，就连选帝侯伯爵本人也承认，他有权统治西南部的平民。如今，斯特凡掌管着一个他鲜少涉足的宫廷，因为还有敌人等着他去斩杀，此刻他正在四处猎杀他们。 "/>
  		<string id="pLS5UtuM" text="西本托德"/>
  		<string id="SoSOBcgt" text="西本托德家族自吸血鬼战争时期便已存在，他们始终留意着不死者的动向，天晓得还盯着别的什么。如今奥斯特马克仍安然无恙，受到保护，这足以证明他们的行动卓有成效。不过，他们的工作似乎永远也做不完，可那又怎样呢？只要奥斯特马克的旗帜还在阴森低地的上空高高飘扬，只要西本托德家族还稳坐其位，不死者就休想作祟。 "/>
		
		<!-- Hochland faction -->
  		<string id="UKGXdiIW" text="冯·卢登多夫"/>
  		<string id="3Zx4JXUR" text="卢登道夫家族是霍克兰当之无愧的主人。阿尔德布兰德在他的子民当中享有极高声誉。这片土地面临着诸多危险，比如来自德拉克瓦尔德森林的野兽人，或是中山区另一边蠢蠢欲动的混沌势力。卢登道夫和他的儿子们竭力坚守阵地，抵御所有威胁，拼尽全力保卫霍克兰乃至整个帝国。 "/>
  		<string id="FDTZimEY" text="冯·哈尔贝瓦尔德"/>
  		<string id="NeRcpsQO" text="此地由近期过世的维克多·冯·哈尔贝瓦尔德的双胞胎之一统治，路德维希仅仅早出生两分钟，因此被视作哈尔伯瓦尔德家族的正统统治者。家族财富源于德拉克瓦尔德森林中的众多猎场以及中山区的矿山，他们向帝国南部售卖各类资源与兽皮。这对兄弟的差别之大超乎想象。路德维希不仅热爱枪支，还是个出色的商人，能将矿山与猎场的开发利用最大化。而另一方面，贝恩德则心系民众，他全身心投入对塔尔的信仰，通常只取用大自然的馈赠。虽说兄弟俩截然不同，人们也常能看到他俩争吵，但对家族与土地的热爱高于一切，为了守护它们，他俩愿意并肩赴死。 "/>
  		<string id="Zxq6w1ql" text="冯·霍亨施泰因"/>
  		<string id="duN05u6j" text="霍亨施泰因家族的财富建立在省内的木制品生意上。他们在德拉克瓦瑟河与弗拉施岗河沿岸拥有数家锯木厂。尽管面临着形形色色的野兽人威胁，他们从未让生产停滞。他们的木材大多用于制作家具，但更重要的是，这些木材被用来打造著名的霍克兰长步枪。虽说他们的木材本身并没有什么特别独特之处，但在枪匠群体中却格外出名。在整个霍克兰，他们的生意是为数不多的高利润生意之一。 "/>

		<!-- Nordland faction -->
  		<string id="bDzinzuk" text="高瑟"/>
  		<string id="Rba25UBx" text=""/>
  		<string id="qsrl1kSI" text="萨尔茨布鲁特"/>
  		<string id="QBoSEpww" text=""/>
  		<string id="h2NAlRBA" text="梅尔戈特"/>
  		<string id="UBzqMjAB" text=""/>

		<!-- Ostland faction -->
  		<string id="UiEZfZhU" text="冯·劳科夫"/>
  		<string id="FwZr8yT6" text="奥斯特领目前的统治家族，尽管是一个古老而高贵的家族，向来以对皇帝的长久忠诚而闻名，但他们直到近期才登上大公国的统治地位。瓦尔米尔·冯·劳科夫是在之前的奥斯特领领主被指控为异端和叛国之后，受封掌管该省，以恢复当地的稳定。这个家族在复杂的政治和宗教环境中接手权力，责任重大。在被授予统治权之前，奥斯特领由于之前领主的不当行为，想必处于一种动荡不安的状态。瓦尔米尔·冯·劳科夫领导下的家族需要应对各种遗留问题，包括但不限于处理旧领主的残余势力、安抚民心、恢复与教会和其他贵族家族的关系等诸多事务。他们不仅要证明自身的忠诚，还要展现出卓越的治理能力，才能让奥斯特领真正重回稳定繁荣的轨道。"/>
  		<string id="uzpRef52" text="冯·斯特鲁特"/>
  		<string id="kDXMYNFO" text="在奥斯特兰西部的大部分地区，中山区占据主导地位。重要堡垒、驻军地和城镇的领主们肩负着守卫关键山口和路径的重任。那些担任守卫的人通常处于冯·施特鲁特元帅的监管之下。这些领主的职责至关重要，因为这些山口和路径很可能是贸易路线、军事要道或者是抵御外敌入侵的关键防线。中山区的地形复杂，为防御工作提供了一定的天然优势，但同时也给后勤保障和信息传递等方面带来诸多困难。冯·施特鲁特元帅在这个防御体系中起到统筹协调的关键作用，他需要确保各个据点之间能够有效配合，信息通畅，物资充足，以应对可能来自山区内部的混沌势力、野兽人或者其他外部威胁。"/>
  		<string id="1bNjVdBb" text="北方戍边领主"/>
  		<string id="xdH2u3hY" text="虽然大亲王瓦尔米尔拥有北方边疆总督这一正式头衔，但真正尽责地在奥斯特兰北部与东部边境保持持续警戒，抵御诺斯卡劫掠者与混沌大军入侵的，却是当地的各位领主。大亲王身负头衔，意味着要统筹全局，处理诸多内政外交事务，精力难免分散。而边境的领主们直面威胁，他们熟悉当地地形与民情，能迅速组织起防御力量。诺斯卡人的劫掠往往突然且猛烈，混沌势力更是神秘而危险，这些领主经年累月枕戈待旦，筑起守护奥斯特兰的第一道防线，守护着身后的土地、百姓与帝国的安宁。 "/>
  		<string id="e4JEtXol" text="北塔拉贝克联盟"/>
  		<string id="lKVF1Ukg" text="北塔拉贝克（奥斯特兰最南端的区域）的城镇与贸易站，尤其是坐落在塔拉贝克河沿线的那些，依照奥斯特兰的标准而言，大体上都很国际化。它们不光能从与帝国南部、西部省份的贸易中获利，还因临近乌尔斯科伊河与塔拉贝克河的交汇处，从而靠近基斯里夫的扎瓦斯塔以及基斯里夫本土，收获不少益处。从贸易货物上看，来自南方帝国省份的精致织物、金属制品，西边的美酒、香料等货物在此汇聚，满足本地多元的消费需求，同时也被转运分销到北方。和基斯里夫的接近更是关键，基斯里夫的厚实皮毛、耐寒牲畜等特产顺着河运或陆路商道来到这里，丰富当地物资储备的同时，也催生了不少转手贸易，让这些城镇和贸易站的经济愈发活跃，文化交流也愈发频繁，街头巷尾常能见到不同服饰、口音的商人往来穿梭。 "/>

		<!-- Brass Keep faction -->
  		<string id="0JW0M8sB" text="携疫征服者"/>
  		<string id="aDsJWBpp" text=""/>
		
		<!-- Wasteland faction -->
  		<string id="o2ly7UXl" text="冯德屈佩尔"/>
  		<string id="S4lBRv2Y" text="扬·范·德·凯珀斯，据说堪称世界首富，无疑也是玛丽恩堡最有影响力的人物。虽说他既不率军冲锋在前，也未端坐王座之上，但比起旧世界的许多国王，他权势更盛。他借助精心培植且威逼利诱得来的盟友与傀儡集团，操控着督政府——这片荒芜之地的寡头议会。这一集团成员不限于执政官、“十人议会”中的其他几位议长、亨里克男爵学院的院长，以及至少两个宗教教派的大祭司。然而，尽管范·德·凯珀斯对玛丽恩堡政治的掌控看似牢不可破，但形形色色的敌对派系也不容小觑 。这些对手或许一直在暗处蛰伏，等待时机，只要他稍有疏忽，就会发起挑战，试图打破他的霸权，为自己争得一份权力与财富，让玛丽恩堡的政治风云更加变幻莫测。 "/>
  		<string id="hWVUkw0w" text="曼纳恩教会"/>
  		<string id="hL9AeRCK" text="海洋之神玛南的教会总部位于玛丽恩堡，是这片荒芜之地最富有、最具权势的宗教组织。卡米尔·多芬娜女族长是该教会在旧世界北部的名义领袖，她是个中年女性，务实且诙谐风趣。她和玛丽恩堡的大多数商业家族都有往来，还利用信天翁修会的领航员、飞行员与牧师来留意国际商业事务。她的这些举动，再加上她不惜重金为大神庙委托打造新的建筑工程，让玛南教会的一些神职人员觉得，她正在把教会变成一个商业行会——敌对的亨德里克教会可太乐意渲染这种说法了。 "/>
  		<string id="ySUUMb7Q" text="登·欧韦"/>
  		<string id="jVrQ251w" text="登·尤韦家族虽然规模不大，但通过经营来自日本和震旦的奇珍异宝，以及各类珍贵宝石与金属的贸易，积累了极为可观的财富。直到不久前，该家族还是扬·范·德·凯珀斯所主导的小集团中的一员，不过，家族族长卡尔如今觉得，扬的财富与影响力已威胁到玛丽恩堡微妙的权力制衡。于是，登·尤韦议长小心翼翼、循序渐进地与富格斯家族、范·登·尼门克斯家族、德·罗勒夫斯家族、范·昂德佐克尔斯家族，以及莎莉雅教会建立起联系，由此形成了一个不容小觑的潜在势力集团。 "/>
  		<string id="xB2ZhJW3" text="范·哈根"/>
  		<string id="caheS5LF" text="克里斯皮恩是范·哈根家族的继承人，众人皆知他是个寻欢作乐、爱冒险、好炫耀的败家子。但这只是部分事实，因为他继承了父亲的政治手腕与强大个性，只是欠缺那份谨慎与自律。克里斯皮恩还是个大胆且凭直觉行事的指挥官，虽说尚未经实战检验。急于摆脱父亲长久以来的阴影、证明自身实力的他，这位“高德伯格的趾高气扬的公鸡”，近来开始亲自指挥范·哈根家族庞大私人卫队中的部队。 "/>

		<!-- Couronne faction -->
  		<string id="odufiEU4" text="德·哥隆尼"/>
  		<string id="VFk73tnZ" text="哥隆尼公国是巴托尼亚的一个创始公国，位于巴托尼亚王国的北岸。这里是国王宫廷的所在地，宫廷就位于公国境内，同时也是王国的首都 —— 库罗纳城堡的所在地。"/>
  		<string id="i5pbgCY7" text="荣誉骑士团"/>
  		<string id="jIdIBHpZ" text="荣誉骑士（Chevaliers D'Honneur）是国王的挚友与支持者。那些为王室立下赫赫战功之人，会获封这一荣誉头衔。该群体的成员曾为国王路易恩完成诸多重要任务，历经数场大战，已然证明他们是王国与国王的忠诚骑士。这些荣誉骑士在巴托尼亚的社会与军事架构里占据特殊位置。于社交层面，他们能频繁出入宫廷，与国王直接交流，这赋予他们极大的影响力，其他贵族往往会对他们格外敬重，渴望与他们结交，期望借此沾上国王的恩宠，或是打听宫廷内的最新动向。在军事上，每逢大战，他们常被委以重任，率领精锐部队冲锋陷阵，他们的战斗经验与英勇无畏，不仅激励着普通士兵，还能在战局胶着时，凭借高超战术与无畏斗志扭转乾坤，守护王国的安稳。 "/>
  		<string id="BUmewEao" text="蒙米莱尔的勇士"/>
  		<string id="X6kJSgs6" text="蒙米赖的勇敢骑士团由罗兰元帅统领。他们肩负着保卫库罗纳公国东部与玛丽恩堡之间边境的重任。这片边境地区界限模糊，并没有明确划定的实际边界。罗兰元帅一有机会就试图扩张领土，这在巴托尼亚与玛丽恩堡之间引发了不少冲突。罗兰元帅这么做，一方面是出于对荣耀与土地的追求，在巴托尼亚的封建体系里，土地就意味着财富、权力与声望，为家族和骑士团谋取更多封地，能巩固自身地位。另一方面，从战略上看，抢占先机控制更多边境区域，有利于未来的防御布局，让己方在面对玛丽恩堡潜在的军事威胁时，拥有更广阔的缓冲地带。只是他的这种扩张行为，无疑让两国关系愈发紧张，随时可能升级为大规模军事对抗，给边境百姓的生活也带来诸多不安定因素。 "/>

		<!-- Anguille faction -->
  		<string id="CDIysBhx" text="勒安谷"/>
  		<string id="gQZKegWb" text="朗吉耶，正式名称是朗吉耶公国，是巴托尼亚的一个公国，坐落在王国的北岸。它因拥有巴托尼亚境内一些最为繁忙的港口而闻名遐迩，是个极为富庶的公国，财富在很大程度上依赖于海上贸易。正因如此，在其首府的农民群体当中，有大量的商人和中产阶级平民。在朗吉耶公国，港口的繁荣带动了一系列产业发展。每日都有来自不同地区的商船停靠，卸下异国的货物，诸如震旦的丝绸、旧世界其他国度的香料与美酒，同时装上本地的特产，像优质羊毛、手工打造的精美银器准备外销。商人们借此大发其财，积累起财富后，不少人从普通农民阶层跃升为中产阶级。这些新兴的中产阶级平民又进一步活跃了本地市场，开设店铺、钱庄，让公国首府的经济愈发多元且充满活力，与传统巴托尼亚纯粹以农业和骑士封建体系为主导的经济模式稍有不同。 "/>
  		<string id="e3emrh8q" text="灯塔弟兄会"/>

		<!-- Lyonesse faction -->
  		<string id="Lx3GfJfd" text="里昂尼斯"/>
  		<string id="XP3v2fRm" text="莱昂内斯，正式名称为莱昂内斯公国，是巴托尼亚的创始公国之一，位于该国的西北海岸。作为较大的公国之一，莱昂内斯的领地因其内部贵族间的纷争而声名狼藉，这种纷争并非源于和其他巴托尼亚公国的竞争，即便相较于困扰巴托尼亚其他地区的封建冲突，这里的内斗也尤为严重。人们将这种激烈的内讧归咎于公国不同寻常的地理环境，尤其是大量绝佳的筑垒地点，这使得其他公国不敢轻易对莱昂内斯的领主们发动战争或挑起宿怨。这些易守难攻的堡垒使得莱昂内斯的贵族们割据一方，各自为政。每个贵族都坐拥坚固的据点，自信能抵御外部威胁，于是将更多精力放在与本地其他贵族争夺领地、资源或是威望上。比如，围绕某条河流流经区域的肥沃土地归属，或是一处矿山的开采权，贵族们频繁爆发冲突，严重阻碍了公国的整体发展，让本该用于对抗外敌、拓展巴托尼亚王国影响力的人力、物力，都消耗在了无休无止的内部争斗之中。 "/>

		<!-- Artois faction -->
  		<string id="0r2pgnNv" text="阿尔托瓦"/>
  		<string id="u4Y7cPTo" text="阿尔托瓦，正式名称是阿尔托瓦公国，是巴托尼亚的一个创始公国，位于该国北部的中心地带。与巴托尼亚其他公国那郁郁葱葱的草地不同，阿尔托瓦闻名之处在于，它是唯一一个全境都被森林荒野覆盖的公国，巴托尼亚人将这片森林称作阿登森林。正因如此，该公国始终处于与野兽人部落的交战状态，这些野兽人已把这片森林当作它们新的黑暗家园。在阿尔托瓦，生活充满艰辛与危险。森林的茂密植被为野兽人提供了绝佳掩护，它们能借此发动突然袭击，掠夺村庄、屠杀村民。公国的骑士与士兵们必须时刻保持警惕，频繁穿梭于林间巡逻。由于野兽人的繁衍速度较快，且熟悉森林地形，阿尔托瓦的防御作战往往极为艰难。不过，长期的战斗也锤炼出了公国军队坚韧不拔的作战风格，他们熟练掌握在森林环境下作战的技巧，利用树木设置陷阱、搭建隐蔽的瞭望哨，与野兽人展开一场场残酷又持久的生存之战。 "/>

		<!-- Gisoreux faction -->
  		<string id="XWJw0y4M" text="吉索莱奥"/>
  		<string id="0oe9dFIP" text="吉索莱奥，正式名称是吉索莱奥公国，是巴托尼亚的一个创始公国，坐落在苍白姐妹山的险峻山坡与阿登森林的低矮林地之间。与巴托尼亚其他地方不同，这里的土地并非只有单一地貌，居民也并非只有单一类型，公国地理环境的多样性造就了文化与习俗的多元性。在南部的可耕平原上，生活着巴托尼亚各地都常见的普通农民。往东，土地上满是荒芜的林地，居住着另一群人，他们是经验丰富的猎人和荒野樵夫。最后，在北部，那些能在苍白姐妹山艰难求生的，都是饱经风霜的登山者，他们不惧恶劣环境。公国还拥有吉索雷峡谷，这是整个灰色山脉仅有的三个可供巴托尼亚与帝国往来通行的通道之一。这条峡谷极具战略意义，它不仅是贸易路线的关键节点，让两边的货物、技术得以交流，也是军事上的咽喉要道，一旦有战事爆发，谁控制了峡谷，谁就能在攻防上占据先机，无论是巴托尼亚抵御帝国可能的南下入侵，还是帝国阻挡巴托尼亚北上的军事行动，吉索雷峡谷都必然会成为争夺焦点。 "/>

		<!-- Parravon faction -->
  		<string id="ffVYYOKc" text="德·帕拉翁"/>
  		<string id="k5UDw2fn" text="在灰色山脉的南端，坐落着巴托尼亚的帕拉冯领地。帕拉冯掌控着从灰色山脉直接通往帝国的三条路线之一，也就是灰女士山口。由于该公国既位于山脉底部，又深入灰色山脉内部，帕拉冯人对栖息在山顶的天马有着特殊的亲近感。事实上，帕拉冯公爵卡西安·德·帕拉冯已经和所有天马的首领戈尔菲纳尔结为好友。这份独特的友谊给帕拉冯带来不少益处。在军事方面，天马速度极快且能翱翔天际，战时它们可为帕拉冯传递紧急军情，比常规的信使快上许多，让公爵能迅速应对边境的突发状况，或是组织起防御力量。从文化层面看，与天马的亲近加深了帕拉冯在巴托尼亚诸领地中的独特地位，吟游诗人传颂着公爵与天马之王的故事，吸引各地旅人前来，促进当地文化交流的同时，也带动了贸易发展，毕竟游客们会购买当地特产，还可能把外面新奇的货物引入。 "/>

		<!-- Montfort faction -->
  		<string id="F2wNjob0" text="德·蒙福特"/>
  		<string id="QC4XcWEz" text="蒙福尔的城堡位于巴托尼亚南部省份帕拉冯以北、巴托尼亚东部。和帕拉冯一样，蒙福尔公国既处于灰色山脉之中，也延伸至山脉脚下。蒙福尔境内有一条从灰色山脉通往帝国的三条通道之一，即斧咬山口 。由于身处山区，蒙福尔人本身就是坚韧的山地居民。频繁遭受劫掠让他们对外族，也就是非人类，比如矮人、半身人和精灵，产生了偏见。长期以来，蒙福尔饱受战乱之苦，那些外族商队或是旅人路过时，常被当地居民投以怀疑的目光，贸易往来也受到限制。矮人携带的精良武器、半身人烘焙的美味点心、精灵制作的精美工艺品，原本能丰富本地生活，却因这份偏见，难以顺畅进入蒙福尔市场。而且在遭遇危机时，本可携手合作对抗外敌的机会，也可能因为这份排外情绪而错失，让蒙福尔公国在应对外部威胁时少了几分助力。  。由于身处山区，蒙福尔人本身就是坚韧的山地居民。频繁遭受劫掠让他们对外族，也就是非人类，比如矮人、半身人和精灵，产生了偏见。长期以来，蒙福尔饱受战乱之苦，那些外族商队或是旅人路过时，常被当地居民投以怀疑的目光，贸易往来也受到限制。矮人携带的精良武器、半身人烘焙的美味点心、精灵制作的精美工艺品，原本能丰富本地生活，却因这份偏见，难以顺畅进入蒙福尔市场。而且在遭遇危机时，本可携手合作对抗外敌的机会，也可能因为这份排外情绪而错失，让蒙福尔公国在应对外部威胁时少了几分助力。 "/>

		<!-- Bastonne faction -->
  		<string id="kofGJYox" text="德·巴斯托涅"/>
  		<string id="X1pJaLGK" text="巴托尼亚的正中心坐落着巴斯通内公国。它不仅地处中心位置，许多人还坚信巴斯通内就是巴托尼亚的心脏。由吉勒斯·勒·巴托尼亚建立的女神教会大教堂，就坐落在巴斯通内城堡的城墙之内。据说，就在沙隆森林里，吉勒斯和他的同伴们首次邂逅了女神。正因为巴斯通内是巴托尼亚的心脏，这里的民众堪称巴托尼亚人中最为傲慢自负的。巴斯通内公国麾下汇聚了巴托尼亚大部分的圣杯骑士，它也理所当然地宣称自己是所有公国中最为重要的一个。在这片土地上，圣杯骑士们的英勇事迹被反复传颂，激励着年轻一代投身骑士修行，期望有朝一日能加入这一荣耀群体。每逢重大节日，巴斯通内城堡前的广场上都会举行盛大庆典，展示公国的财富、武力与荣耀，引得各地贵族、平民纷纷前来瞻仰，进一步巩固其在巴托尼亚至高无上的地位。 "/>
  		<string id="mzQF8rZy" text="德·卡拉德"/>
  		<string id="bufJpPO9" text="在巴斯通内公国，加拉蒙家族的名号向来备受敬重。不过，直到他父亲离世，加拉蒙家族才在整个巴托尼亚王国声名远扬。卡拉德斩杀了一名野兽人军阀，为刚刚战死的父亲报了仇，也将波尔德罗从这场严重的威胁中拯救出来。这场战斗堪称传奇，彼时波尔德罗危在旦夕，野兽人部落倾巢而出，烧杀抢掠。卡拉德的父亲身先士卒，却不幸战死沙场，这激起了卡拉德的满腔怒火与无限斗志。他单枪匹马冲入敌阵，凭借着高超的武艺与无畏的勇气，在血腥混战里寻得野兽人军阀，一番激战之后，成功将其斩于马下。经此一役，卡拉德成了英雄，加拉蒙家族的声望如日中天，各地的吟游诗人纷纷传唱他的英勇事迹，贵族们也对这个家族更为尊崇，不少年轻骑士更是以卡拉德为楷模，期望能效仿他守护家园、建功立业。 "/>

		<!-- Bordeleaux faction -->
  		<string id="fAjG5E3I" text="德·波尔德罗"/>
  		<string id="ffqBrTCf" text="阿尔贝里克公爵麾下的队伍十分有趣。唯有最为坚毅且才华出众的骑士，才会长时间获许与这位波尔德罗公爵并肩作战。正因如此，受托守护王国安全的这些人，都是整个巴托尼亚最有能耐的战士，也是风格独特的贵族。这些骑士和贵族之所以出类拔萃，原因有诸多方面。从训练上讲，公爵对他们的要求极为严苛，日常的骑术、剑术训练远超普通骑士团标准，还时常模拟各类极端战况，比如在暴雨泥泞中作战、应对数倍于己的敌军突袭，借此锤炼实战能力。再者，公爵偏好招揽有独特本领或背景的人，有的骑士或许出身神秘古老家族，身负失传剑术秘籍；有的贵族则游历过遥远异国，能带来新奇战术思路与见闻，让整个队伍既勇猛善战，又充满别样魅力与活力，在守护波尔德罗乃至巴托尼亚时，更具优势。 "/>

		<!-- Brionne faction -->
  		<string id="Sg4QDt1i" text="德·布里奥涅"/>
  		<string id="QJFdscVQ" text="有人说，任何出生在布里奥涅的人都有一颗诗人的灵魂。在这里，诗歌与武艺同样重要。该地区的城堡和堡垒似乎也在助力达成这一氛围。许多城堡建在几乎毫无防御优势的地方，只为与周遭风景相契合，甚至还修建了带有大窗户和座位的塔楼，只为聆听吟游诗人的吟唱，而非出于防御目的。在布里奥讷，春日暖阳洒落在古老城堡的石墙上，斑驳陆离。城堡主人时常邀请各地知名的吟游诗人，于塔楼窗边落座。微风轻拂，伴随着悠扬的鲁特琴声与诗人的浅吟低唱，贵族与百姓们一同沉醉其中。远处，手持长剑训练武艺的骑士们，训练间隙也会仰头倾听，对他们而言，剑可护国安邦，诗歌亦能滋养心灵。这种对诗意生活的追求，早已融入布里奥讷人的日常，超脱了战争与防御的实用考量，塑造出独有的浪漫气质。 "/>

		<!-- Quennelles faction -->
  		<string id="lDFVHWru" text="德·昆涅尔斯"/>
  		<string id="PlfTryNU" text="奎内尔的民众狂热地致力于彻底消灭绿皮兽人，尤其是那些从奥卡尔山区下来掠夺他们土地的家伙。当地的寻路骑士在矮人当中格外有名，因为他们中有许多人会在圣杯探索之旅中冒险进入旧世界的山脉与荒地。即便如此，历经数百年尝试剿灭奥卡尔山区的绿皮并对其殖民，绿皮兽人依旧是公国持续存在的威胁。为何奎内尔相较于邻国，饱受绿皮兽人肆虐之苦，至今仍是个谜；有人猜测，奎勒克斯的后裔可能遭到了诅咒。绿皮兽人繁殖迅速、好战且贪婪，一次次冲击着奎内尔的防线。那些寻路骑士虽然英勇无畏，不断深入敌巢，可只要山区里还有残余的绿皮部落，就随时能集结起来再度进犯。至于那个诅咒的传言，倘若属实，或许就解释了为何绿皮仿佛认准了奎内尔，无论当地军民如何奋力抵抗，都难以摆脱这一长久祸患。 "/>
  		<string id="TdTjzMXP" text="仙子之眷"/>
  		<string id="zhFMijri" text="作为巴托尼亚同一枚硬币的两面，没有其他角色能比圣杯骑士和湖神侍女更能体现巴托尼亚的权势、信仰与传统了。在战场上与他们中的任何一位对阵，都等同于感受到湖中女神本人的神圣怒火，而要是在同一个战场上面对他们二人，那可就恐怖得多了。不知为何，莱昂爵士与玛蒂尔德女士几乎从不分开。战时，这二人组成近乎势不可挡的组合；和平时期，这却引出了许多让多数巴托尼亚人不知该如何作答的尴尬问题。人们对他俩形影不离的关系揣测纷纷。有些保守的贵族觉得，未婚男女如此亲近有违传统礼教，可又忌惮质疑这两位深受女神眷顾之人。从战斗配合来看，圣杯骑士勇猛无畏，冲锋陷阵，湖神侍女则能以神秘法术从旁协助，治愈伤口、驱散敌方邪恶魔法，互补的能力让他们所向披靡。可到了日常宫廷社交场合，他俩旁若无人的默契，又让旁人既羡慕又困惑，成为贵族们茶余饭后私下议论的热门话题。 "/>

		<!-- Aquitaine faction -->
  		<string id="arUeb4rz" text="德·阿奎坦"/>
  		<string id="ohrYjgJD" text="阿奎坦是一片宁静的地区，其地貌几乎全由山谷构成，山谷中遍布牧场与葡萄园。这里产出的名酒，不仅让公国以此命名，还被赋予了催情的特性。阿基坦也是吉勒斯·勒·巴托尼亚经历诸多战役的地方，正因如此，在这片土地上时常能看到众多圣杯骑士的身影。当地的居民大多以农牧业和酿酒业为生，过着闲适的生活。每日清晨，牧人赶着牛羊去往丰美的草场，葡萄园中的工人则开始悉心照料葡萄藤，检查果实的生长状况。阿基坦的葡萄酒举世闻名，每年新酒酿成之际，各地的商人和贵族纷至沓来，采购美酒，让小镇和村庄热闹非凡。而圣杯骑士的频繁出没，更为此地增添了几分传奇色彩，他们或是在古老战场缅怀先辈，或是守护着某些蕴含神秘力量的遗迹，引得不少吟游诗人也汇聚于此，收集素材，传唱那些英勇无畏的过往。 "/>

		<!-- Carcassonne faction -->
  		<string id="36Fdikjb" text="德·卡尔卡松"/>
  		<string id="UrOBGxA6" text="卡尔卡松是一个高度尚武的公国，极为重视军事化建设，并且把剿灭伊拉纳山区的绿皮兽人部落当作重中之重。在卡尔卡松，几乎每个人，从最底层的农民到最高贵的贵族，都是战士。卡尔卡松与布里奥讷联系紧密，这源于卡尔卡松人对诗歌与音乐的喜爱。他们谈及布里奥讷时，常说：“我们作战，是为了让布里奥讷人无需作战。”卡尔卡松的日常景象处处彰显着尚武精神，村庄里，农夫放下锄头就能拿起刀剑，参与抵御绿皮的突袭；城镇中，工匠们在打造农具之余，也精心锻造武器铠甲。孩子们从小就接受战斗训练，学习骑马、射箭与格斗技巧。而每逢节日，人们又会放下武器，聚在一起聆听来自布里奥讷的吟游诗人吟唱，沉浸在诗歌与音乐营造的美好氛围里，用文艺慰藉平日征战的疲惫身心。 "/>
  		<string id="svzY9l45" text="女神眷顾"/>
  		<string id="HIIJnGe6" text="雄伟的瓜达隆城堡矗立在沃尔斯山麓，俯瞰着卡尔卡松与洛伦森林以及提利尔领地的边界。城堡之主，圣杯骑士阿玛里克·德·瓜达隆爵士，是一位强大的勇士，由湖中女神亲自选定，成为巴托尼亚的天选战士。为协助他，湖神女巫派遣了都灵的双胞胎湖神侍女朱丽娅和玛格丽塔来到他身旁，在激烈战事之中及平日，为他提供助力与建议。阿玛里克爵士身负守护边境之重任，时刻警惕着来自洛伦森林精灵的潜在威胁，以及提利尔方向的复杂局势。他武艺高强，骑术精湛，每逢战事，总是一马当先冲入敌阵，令敌人胆寒。而双胞胎侍女则各展其能，朱丽娅擅长治愈魔法，能在激战间隙迅速为伤者疗伤，稳定军心；玛格丽塔精通防护与驱散法术，抵御敌方魔法冲击，让己方免受邪术侵害。三人默契配合，让瓜达隆城堡坚如磐石，守护着卡尔卡松的安稳。 "/>

		<!-- Mousillon faction -->
  		<string id="SyI841r9" text="德·穆席隆"/>
  		<string id="qm1LEakx" text="穆席隆公国是一片憔悴且令人畏惧的土地，到处是沼泽与被诅咒的泥沼。这是片贫困潦倒的地方，疾病肆虐，当地许多居民对此早已习以为常。正因如此，相较于普通巴托尼亚农民，许多穆西隆人都被视作变种人和怪人。村庄与城堡濒于坍塌，夜晚则有幽灵鬼怪和邪恶野兽出没。只有傻瓜和死人，才会在夜里离开家门。在这里，生存是一场残酷的挣扎。白天，村民们拖着病弱身躯，艰难地从贫瘠土地里刨出些许吃食，还要时刻提防着沼泽里突然蹿出的未知生物。那些摇摇欲坠的城堡，昔日的辉煌不再，只剩残垣断壁，贵族们也大多穷困潦倒，无力修缮。一到夜晚，黑暗笼罩，凄厉的嚎叫声回荡在湿冷空气中，家家户户紧闭门窗，在恐惧中熬过漫长黑夜，期盼黎明能带来一丝短暂安宁，可新的一天往往只是重复前一日的苦难与绝望。 "/>
  		<string id="WTyNH3Fm" text="沙托阿纳"/>
  		<string id="qVpeLWal" text="奥卡辛家族世世代代居住在阿内城堡，他家的家族史诗在整个巴托尼亚算是篇幅最长的之一。他的祖先曾为马尔德雷德对抗国王而战，在此之前，还曾为梅罗韦奇对抗莱昂内斯公爵。虽说奥卡辛家族在战场上战功赫赫，但他们更为人所知的，是作为艺术的赞助者与宫廷文化的典范，而奥卡辛本人更是穆西隆最有文化素养的贵族。他在气派的阿内城堡中举办宫廷聚会，邀请诗人与艺术家来为前来拜访的贵族们助兴（这些贵族中就包括马洛鲍德本人 ）。奥卡辛俨然成了穆西隆贵族文化的核心。在这片衰败阴森的公国里，阿内城堡仿佛是一方净土，诗歌的吟诵声、画笔的摩挲声打破死寂，贵族们在此暂别日常的困苦与恐惧，沉浸于高雅艺术营造的美妙氛围，交流着从古老书籍里翻出的奇闻轶事，或是探讨新创作的乐章与画作，为灰暗的穆西隆增添了一抹难得的亮色。 "/>

		<!-- Moot faction -->
  		<string id="sN3YW5OO" text="半身人"/>
  		<string id="rRCoUnrf" text="半身人是一群爱好和平且友善的民族，他们热衷于节庆活动与大型宴会，喜爱玩乐，尤其钟情美食。这是一个没什么野心的族群，所以他们不太关心军事事务，对自家土地之外发生的事也没什么兴趣。正因如此，对于年轻的半身人来说，族里的生活常常十分无趣。尽管半身人普遍不喜欢旅行，但还是有些年轻人会去外面的世界寻求冒险。这些怀揣冒险梦的半身人，告别熟悉的温暖炉火与堆满美食的餐桌，踏入陌生又充满未知的广阔天地。他们可能遭遇凶狠的兽人、神秘的魔法生物，当然也会结识新的朋友，见识到从未见过的奇妙景观，在惊险刺激中，为平淡的半身人生活书写别样的精彩篇章。 "/>

		<!-- Wood Elf faction -->
  		<string id="zwWuwc6l" text="塔塞恩"/>
  		<string id="pA9sEaGn" text="塔塞恩位于艾瑟洛伦的中心，这里是最大、最繁荣的国度，也是阿苏尔（木精灵）人口最为密集的地方。不仅有艾丽尔和奥利安的居所——国王林地，还有岁月之橡坐落于此。在这片国度，树灵与阿苏尔之间的羁绊最为牢固。由于此地囊括了木精灵的核心地带，它成了他们最为神圣的避难所。生活在塔尔辛的木精灵享受着与自然无比亲近的生活。每日清晨，他们在鸟儿的歌声与树叶的沙沙声中醒来，接着便开始照料周边的树木与花草，凭借着世代相传的技艺，让植物愈发茁壮。而树灵们也时刻守护着精灵，当有外敌入侵，无论是贪婪的人类盗猎者，还是残暴的绿皮兽人，树灵都会与精灵并肩作战，用粗壮的枝干、缠绕的藤蔓抵御敌人，阿苏尔则以精准的箭术和灵动的剑术反击，二者协同守护这处圣地的安宁与繁荣。 "/>
  		<string id="NyRdtJhF" text="安米尔"/>
  		<string id="oGfwyFw3" text="当莫尔古尔在高等国度安米尔被击败时，他的鲜血缓缓却持续地侵蚀着这片森林。安米尔，也被称作凋零之握。年复一年，野兽人部落愈发壮大，每年都有更多的森林精魂陷入混乱与堕落。虽说其他国度都察觉到了这一情况，也纷纷施以援手，试图净化这份腐败，但毁灭性的力量还是不可避免地越发强大。精灵们为挽救安米尔付出诸多努力，他们派出最精锐的巡林者，试图找出腐败根源；德鲁伊施展净化法术，期望修复受损的自然之力。可野兽人受莫尔古尔邪恶血脉蛊惑，变得愈加凶狠难缠，还不断拉拢新的同类。森林精魂一旦被腐蚀，反而成了助力敌方的存在，攻击昔日同伴。长此以往，即便各方全力驰援，安米尔的衰败之势仍难以遏制，整个国度笼罩在愈发浓重的阴霾之下。 "/>
  		<string id="jsgj9g58" text="安蒂维奇"/>
  		<string id="btid3xfs" text="阿特尔威斯，又称冬之心，是艾瑟洛伦最为寒冷的区域。严酷的气候条件让生活在这片森林的居民更加坚韧、强壮。恶劣的环境使得自然精魂几乎无法用魔法充盈此地，这就意味着该地区的防御完全依靠精灵的保护。难怪永恒卫士在这片区域的殿堂中数量最为众多。在阿特尔威斯，凛冽寒风终年呼啸，冰雪终年不化。精灵们为了生存，练就了超凡的耐寒能力与战斗技巧。永恒卫士们身披厚重战甲，手持坚盾利刃，不分昼夜地巡逻，警惕着任何可能突破防线的威胁。他们深知，一旦松懈，没有自然魔法庇护的家园，就会轻易被外敌踏足，所以哪怕严寒刺骨，也绝不退缩，用钢铁意志与强健体魄，守护着冬之心的安宁。 "/>
  		<string id="bG2XYVmp" text="阿格维隆"/>
  		<string id="HkPa3GKe" text="此地也被称作月泉林地，因其奇妙景观与强大魔力而闻名。与大多数其他国度不同，这里的居民依旧遵循着曾经从乌尔苏安迁徙而来的阿苏尔（高等精灵）的传统、规范与价值观。该地区依然维持着一套严格的官僚体系。正因如此，阿尔格维隆的居民保留着阿苏尔那广为人知的傲慢，也就不足为奇了。在阿尔格维隆，精灵们的生活秩序井然，各项事务皆有章可循，从日常狩猎、耕种的配额分配，到大型节庆、祭祀的流程安排，都由官僚机构精准把控。不过这份刻板与傲慢也常引发矛盾，当外来者踏入这片土地，试图友好交流或是贸易往来时，当地精灵往往会带着高高在上的审视目光，对他人习俗、商品挑三拣四，使得不少本可互利共赢的合作机会付诸东流，给月泉林地蒙上了一层略显孤僻的色彩。 "/>
  		<string id="839vP6oc" text="阿兰洛克"/>
  		<string id="FNm3eP3g" text="有些人把阿拉诺克称作“夏日海岸”，它是艾瑟洛伦的一处高等国度，这里终年不见冬日，夜晚短暂，阳光终年普照。这个国度以其盛宴和热情好客而闻名，即便是和平来访的外族人，也能感受到这份热忱。总体而言，这片国度给人一种平和友善的感觉，不过，一些心怀恶意的树灵，可能会趁人们沉醉于美酒与欢乐、放松警惕之时，为自己谋取好处。在阿拉诺克，每日都是热闹非凡的景象。繁花似锦的草地上，摆满了长桌，上面堆满了鲜美多汁的果实、香醇醉人的美酒。精灵们身着轻薄艳丽的服饰，伴着欢快的乐曲翩翩起舞，欢声笑语回荡在四周。外来旅人初到此地，瞬间便会被这份欢乐氛围感染。只是偶尔，当夜色渐浓、狂欢渐歇，会有诡异黑影在树林间穿梭，趁人不备，悄悄施展些小把戏，或是偷走些珍贵小物件，给这场盛宴添上一丝不和谐的小插曲。 "/>
  		<string id="kFnYkPI1" text="卡瓦洛克"/>
  		<string id="jJ9oOws6" text="卡拉沃克，也被称作天痕边境，位于艾瑟洛伦的最西南端。这里树木相当稀疏，诸多林间空地时常遭到外族侵扰。卡尔卡松的巴托尼亚人把他们的定居点建得离卡拉沃克领地很近，甚至就建在其境内，危险至极。此外，野兽人也常常试图经由这个高等国度的林间空地进入森林。不过，卡拉沃克的子民都是出色的骑手，他们知道该如何保卫自己的土地。面对频繁的外来威胁，卡拉沃克的精灵骑手们时刻保持警惕。他们骑乘矫健的骏马，在稀疏林地与开阔空地间来回巡逻，锐利的目光扫视着每一处可能藏有敌人的角落。一旦发现巴托尼亚人的擅自闯入，骑手们会迅速集结，发出警告，勒令其撤离；若是遭遇野蛮的野兽人来袭，他们便毫不犹豫地发起冲锋，凭借精湛骑术与精准箭术，将来犯之敌击退，守护着这片西南边陲的家园。 "/>
  		<string id="CBOXFU4M" text="塞西拉"/>
  		<string id="PYqgfNN8" text="并非所有树灵都寻求与精灵和谐共处。对一部分树灵而言，精灵打造了一座牢笼，也就是被称作荒木林的赛思拉尔。赛思拉尔的边界由界石栅栏和高等国度的子民守护着。虽说从理论上讲，界石应当能阻拦邪恶树灵，但赛思拉尔的阿苏尔（木精灵）仍需积极捍卫并维护这些界石，以防树灵逃脱。这项任务艰巨又危险，精灵们需定期穿梭于阴森的荒木林周边。界石历经岁月侵蚀、战事冲击，时常出现裂隙或是魔力减弱的状况，精灵们得施展修复法术，重新注入魔力。与此同时，被困的邪恶树灵也会趁机发起攻击，用粗壮枝干、尖锐藤蔓突破栅栏，精灵战士们便要举剑迎敌，在魔法与刀剑的交织中，死死守住防线，不让这些充满恶意的精魂危害艾瑟洛伦的其他区域。 "/>
  		<string id="bpUmRtIs" text="菲尔·达里克"/>
  		<string id="2m9FFJkO" text="菲尔·达里克高等国度，也被称作欺诈者之林，是献给音乐、狂欢、欢乐与诡计之神洛克的。在这片树林里，战舞者们能找到一处安全的庇护所，这并非什么秘密。他们来到此地展现战斗技巧、展开训练并进行决斗。虽说他们的杂技技艺令人赞叹，但日常的训练却极为残酷，竞技场的地面都被鲜血浸染。对许多人来说，竞技场中的战斗往往以死亡收场。每天清晨，阳光洒在林间空地上，战舞者们就已开始热身，拉伸灵活的肢体，准备迎接高强度训练。他们在树枝间飞荡穿梭，用利刃精准切割飘落的树叶，磨砺技艺精准度；两两一组激烈对打时，凌厉腿脚与飞舞刀剑碰撞，稍有不慎，皮开肉绽。而正式决斗时，气氛更是紧张到极点，观众围坐四周，欢呼声、呐喊声交织，参赛者为了荣耀、为了证明自己，全力以赴，每一场对决都是生与死的较量，失败者往往就此倒下，再也无法起身。 "/>
  		<string id="VSm1bTSH" text="莫德伦"/>
  		<string id="4jmkaQIh" text="莫德林，又称暗夜林地，是艾瑟洛伦处于永恒黑夜中的高等国度。这里的森林精魂以及精灵居民，比艾瑟洛伦其他地区的同类更加充满怨恨。莫德林的子民与希萨拉伊诸神结盟，这些神祇通常是黑暗精灵德鲁奇崇拜的对象。莫德林还因黑暗魔法的修习者众多而闻名，在艾瑟洛伦的其他地方，可看不到这么多研习黑暗魔法的人。在这片不见天日的国度，阴森气息弥漫四周。黑暗魔法的修习者们隐匿在阴影之中，钻研禁忌法术，他们召唤出诡异的暗影生物为自己效力，让本就黑暗的林地越发诡谲难测。精灵们也因长期身处黑暗，内心被怨愤填满，对外来者敌意极深，稍有风吹草动，便会发起攻击。森林精魂更是喜怒无常，常给闯入者设下致命陷阱，用扭曲的藤蔓与尖锐的树枝将其困住，莫德林仿佛是艾瑟洛伦的黑暗死角，散发着令人胆寒的气息。 "/>
  		<string id="kCmmKgOr" text="提西茨"/>
  		<string id="NrutWonL" text="据说，在提尔西提斯，从未奏响过欢快的歌曲，只有生活在死亡阴影下的精灵们的挽歌。然而，被称作“灰烬殿堂”的这个高等国度的居民，实际上并不比其他国度的精灵更加宿命论。不过，他们对生命的终结和起始同样敬重。这片国度装饰着月长石，它们是为纪念逝者而放置的。就连自然精魂也尊重这些举动，会在深受爱戴的木精灵身旁长出树林。任何前来扰乱逝者安宁的人，都将激起这些子民的愤怒。每当有精灵离世，族人们便会怀着沉痛的心情，将打磨光滑的月长石安置在特定的林地，那柔和的月光色泽仿佛能慰藉逝者的灵魂。平日里，精灵们路过这些地方，都会轻声祷告，脚步放轻，就连林间嬉戏的小动物也似乎知晓此地的肃穆，安静下来。若有外来者贸然闯入，或是心怀不轨试图破坏月长石，瞬间就会被四周涌出的精灵与警觉的自然精魂包围，迎接他的将是毫不留情的反击，守护着这份对逝者的敬重与安宁。 "/>
  		<string id="e8L0c6Ef" text="托尔戈万"/>
  		<string id="eMdDJ1gY" text="托尔戈万，也叫星光熔炉，是《战锤》奇幻世界观下艾瑟洛伦森林中的重要区域。此地因木精灵工匠的高超技艺声名远扬，受到瓦尔之砧的祝福。瓦尔是战锤世界里的工匠神，这一祝福让托尔戈万的锻造神庙能够产出整个木精灵国度中最为精良的武器。它地处森林核心位置，优越的地理位置使其极易被其他国度的精灵抵达，自然而然地演变成艾瑟洛伦森林各部落间的关键交换站点。精灵们带着各地的珍稀特产汇聚于此，用香料、魔法织物等交换心仪的神兵利器，不仅促进技艺交流，也维系着这片奇幻森林的内部联系与活力。 "/>
  		<string id="2KkWZFOl" text="温德里赫"/>
  		<string id="IdzPuudQ" text="温德里赫国度毗邻灰色山脉的西部地区。过去，有许多侵略者，包括人类、绿皮兽人还有矮人，都试图穿越这片领地，却都未能成功。这里的居民是伏击大师，他们的领地布满了众多藏身之处、秘密前哨站以及隐蔽小径，方便发动伏击。虽说维德里奥思的子民数量远远不及入侵者，但他们有能力生存下来，抵御任何企图闯入木精灵国度的不速之客。每当有外敌靠近，维德里奥思的精灵侦察兵便会迅速隐匿身形，穿梭于树冠之间，悄然追踪敌人的动向。他们精准判断敌军的行军路线，随后悄悄部署兵力，让同胞们埋伏在关键节点。当侵略者大摇大摆踏入预设陷阱，刹那间，利箭如雨般从四面八方射来，精灵战士紧接着从藏身的灌木丛、树洞跃出，挥舞利刃发起冲锋，凭借熟悉地形与默契配合，将敌人杀得人仰马翻，捍卫自家领土的安宁。 "/>
  		<string id="TfaMIcDG" text="暮光姐妹"/>
  		<string id="73iyTmMF" text="暮光姐妹奈斯特拉与阿拉罕，就如同白昼与黑夜般截然不同，然而，从未有人见过她们分开过哪怕一天。奈斯特拉通常更倾向于外交手段而非武力，阿拉罕则只要有机会，就会寻求正面交锋。虽说她们之间的争论常常看起来火药味十足，但正是这种差异达成了完美的共生关系，让她们成为了艾瑟洛伦传奇般的守护者。当外族使者踏入艾瑟洛伦意图商谈领土事宜，奈斯特拉便会面带微笑，用温婉言辞周旋，剖析利弊，劝退那些心怀不轨之人；可一旦遇上蛮横不讲理的侵略者，阿拉罕立刻热血上头，抄起武器就冲锋在前，以凌厉攻势让敌人胆寒。而在战斗间隙，两人又会凑在一起，轻声交流战术，互相打趣，之前的分歧瞬间烟消云散，继续携手守护这片神奇的森林家园。 "/>
  		<string id="WePg1Z2S" text="艳阳守望者"/>
  		<string id="8XoMbgaF" text="日之守望领地大多居住着“托里奥”，他们是艾欧尼尔族中生于城市的亲族。在胡须之战的一系列事件后，随着高等精灵（阿苏尔）的后撤，帝国各地有不少高等精灵前往精灵最后的堡垒寻求庇护。这里的城市生活别有一番风貌，高大的精灵建筑错落有致，白色大理石在阳光照耀下熠熠生辉。街道上，托里奥精灵们往来穿梭，既有身披精美战甲、肩负巡逻守卫之责的卫士，也有身着飘逸长袍、钻研魔法技艺或是古老知识的学者。新到来的高等精灵难民融入其中，带来乌尔苏安的别样文化与技艺，让日之守望在传统之上，又添几分新鲜活力，城市越发繁荣，艺术、魔法的交流氛围愈发浓郁。 "/>
  		<string id="bVYWnB9T" text="雨幕守望者"/>
  		<string id="nIIe8VVj" text="雨幕守望者大部分覆盖着被劳瑞欧恩森林环抱的沼泽地。它与托·利塔内尔直接相连，这使得它成为前往荒地和玛丽恩堡的最快路线，艾欧尼尔精灵时常借此路线与当地高等精灵聚居地进行商业及政治交流。因此，保护这些令人生畏的沼泽地，对这个脆弱的精灵行省来说至关重要。这片沼泽地危机四伏，瘴气弥漫，泥沼暗藏，稍不留意就会深陷其中。可艾欧尼尔精灵却巧妙利用此地，布置了层层防线。他们搭建起隐蔽的高脚屋哨站，精灵战士潜伏其中，凭借超凡视力与锐利听觉，时刻留意着周边动静。一旦有外敌贸然闯入，精灵们或是从迷雾中射出冷箭，或是驱使魔法召唤出的水元素冲击来犯者，让企图破坏商业交流路线或是侵扰行省安宁的势力，葬身于这片险恶沼泽。 "/>
  		<string id="PMKHbvmT" text="风暴守望者"/>
  		<string id="ldq7X287" text="风暴守望守护着劳瑞欧恩森林的北部，掌控着这片森林通往海岸的唯一通道，借此得以与全球各个遥远派系展开贸易。这里的居民和其他守望者一样有强烈的保护欲，但比起旁人，他们与接壤地区的民众，或是在海上相遇的势力交流沟通时更具外交手腕。只要能从中获益，冲突未必会以流血收场，转而促成一笔贸易，这种情况并不罕见。当海盗船或是他国的贪婪商船试图染指这片海岸，风暴守望的精灵舰队便会迅速集结，战船破浪而出，以威慑之势逼停对方。随后，精灵使者登上敌船，不疾不徐地展示自家的珍稀货物，比如用魔法加持的木材、精致的精灵织物，同时点明暴力抢夺的后果，往往能化干戈为玉帛，把潜在的敌手变成贸易伙伴，让海岸贸易持续繁荣，为劳瑞欧恩森林带来源源不断的物资与财富。 "/>
  		<string id="0s9Ltnz7" text="森林守望者"/>
  		<string id="i3HkwVxh" text="风暴守望负责守护劳瑞欧恩森林的北部区域，把控着这片森林通向海岸的唯一路径，有了它，精灵们才得以与世界各地的诸多势力开展贸易往来。这里的居民和其他守望者一样，有着守护家园的本能，但相较而言，他们在面对接壤地区的族群，或是在海上狭路相逢的势力时，更擅长交流沟通，也更精通外交策略。只要能从中获取好处，那么一场冲突未必就会演变成血腥厮杀，反倒有可能促成一笔买卖。精灵们清楚这片海岸通道的重要性，为此建立起了完备的防御与预警体系。沿海的瞭望塔上，时刻有精灵哨兵驻守，锐利目光扫视海面。一旦发现陌生船只靠近，精灵巡逻舰队旋即出动。不过，在正式交锋前，精灵使者往往会先登上对方船只，凭借伶俐口才与优雅仪态，试探对方来意，同时展示自家的奇珍异宝，试图开启一场互利共赢的贸易谈判，而非立刻诉诸武力。 "/>

		<!-- Chaos faction -->
  		<string id="5py6WFsS" text="混沌"/>
  		<string id="AUYBC422" text="混沌，是凡人用来描述一种恶性超自然失序精神力量的术语，这种力量折磨着已知世界。它是一股由纯粹魔力构成的强大力量，能够给有感知的生物带来身体变异与精神堕落。打个比方，混沌就如同海洋，是一股持续涌动、由情绪驱动的变幻之力，与主宰自然世界的固定物理法则截然相反。恰似海洋一般，它的力量会随时间时强时弱，不过这股浪潮始终冲击着、试图侵入凡人的存在位面。 在这片被混沌威胁的土地上，普通农夫可能一觉醒来，发现自家牲畜长出怪异肢体，谷物田被诡异迷雾笼罩，收成化为乌有；勇猛的战士也会在某次战斗后，眼神逐渐迷离，内心被黑暗欲望填满，背离曾经坚守的荣耀与正义，沦为混沌的傀儡。各国的巫师与智者们，无不绞尽脑汁，试图找到抵御这股无形却致命力量的方法，守护住来之不易的文明与安宁。  "/>

		<!-- Beastmen faction -->
  		<string id="S8VPHyrK" text="野兽人"/>
  		<string id="NvYX1hLS" text="野兽人是一个野蛮的变异类人种族，他们有着各式各样形似野兽的特征，比如偶蹄、肌肉发达的人类身躯、长着角的兽首，还具备原始而邪恶的智力。野兽人是一个暴力好战、受战争驱使的野蛮变异种族，一心只想侵扰并摧毁人类文明以及凡人世界的其他部分。他们专挑弱者和毫无防备之人下手，毫无预警地袭击孤零零的定居点，在一场破坏狂欢后，便消失在庇护他们的黑暗天性之中，逃避往往并未降临的严厉惩罚。在偏远的边境村落，每当夜幕笼罩，村民们便会战战兢兢，生怕那群可怖的野兽人突然来袭。这些野蛮家伙一旦出现，便会挥舞着简陋却致命的武器，撞开脆弱的栅栏，嘶吼着冲进村子。他们烧杀抢掠，把村民辛苦积攒的粮食、财物席卷一空，还抓走不少人当作食物。等到周边城镇的援军赶来，往往只能看到一片死寂的废墟，野兽人早已遁入深山老林，继续蛰伏，等待下一次血腥肆虐的时机。 "/>

		<!-- Druchii faction -->
  		<string id="7LVvNqBn" text="黑暗精灵奴隶贩子"/>
  		<string id="AwxMDtoS" text="黑暗精灵（德鲁奇）将奴隶制作为首要的经济制度，依靠它来维持他们黑暗的纳迦罗斯王国运转，使其能在持续的战争状态下存续。虽说古代纳迦瑞斯的居民都是无与伦比的勇士，但他们对如何构建一个自给自足的文明却知之甚少。正因如此，马雷基斯的王国依赖袭击其他民族来获取食物，或是抓捕奴隶为他们劳作。在纳迦罗斯那冰冷阴森的土地上，一艘艘黑帆战船频繁出征。它们破浪驶向沿海的人类城镇、精灵聚居地，乃至矮人据点。一旦靠岸，黑暗精灵战士便如鬼魅般杀出，血腥屠戮当地居民，将幸存者用铁链锁住，押送回冰冷的家乡。这些奴隶被驱赶进矿坑，没日没夜地挖掘珍贵矿石；或是在田间辛苦劳作，种植耐寒作物，只为填饱黑暗精灵的肚子，支撑起王国庞大的战争机器，好让德鲁奇继续在仇恨与战火中追逐霸权。 "/>

		<!-- Empire outlaw factions -->
  		<string id="e42CJzj5" text="帝国逃兵"/>
  		<string id="JFJ964lM" text="帝国逃兵是些毫无荣誉感的人，他们逃离了自己的职责，如今过着逃亡者的生活。他们在帝国内四处游荡，从旅人身上偷取钱财，还伏击商队。这些逃兵本应身着帝国的制服，守护疆土、维持治安，却因懦弱或是贪生怕死，选择背弃誓言。他们隐匿在道路两旁的树林、废弃的堡垒当中，一旦瞅见商队满载货物缓缓前行，或是落单旅人路过，便会手持利刃、张弓搭箭，呼啸着冲出来。得逞之后，便带着抢来的财物迅速逃窜，躲进深山老林，在阴暗角落挥霍着不义之财，沦为帝国治安的一大祸患。 "/>

		<!-- Bretonnian Freeroamers-->
  		<string id="oa5ACwZg" text="吟游诗人"/>
  		<string id="1pArmalt" text="特里斯坦这个吟游诗人和朱尔斯这个弄臣是著名的巴托尼亚二人组"/>
  		<string id="ShAd9v5C" text="贝尔格兰特的长弓手"/>
  		<string id="N4nXr93I" text="贝特朗既无意争取成为骑士，也不想跻身贵族行列，而他的追随者们也早已受够了缴纳封建赋税。他们满心想着能把自己种出来的所有东西都留为己用。要是贝特朗立下骑士誓言，他还得舍弃心爱的长弓，因为那被视作不光彩的武器，而这是他绝对不会做的事。于是，贝特朗和他的同伴们开始在巴托尼亚的荒野地区四处游荡，只要有需要，就去匡扶正义，为农民撑腰。多数时候，这意味着要对抗劫掠者与兽人，但偶尔也会碰上某个腐败堕落、毫无荣誉感的男爵或骑士，需要将其击败。贝特朗一伙人在荒野中居无定所，他们像一群不羁的游侠。身上背着简陋的行囊，长弓从不离身，箭筒里插满了精心打磨的箭支。一旦听闻哪个村庄遭遇了匪患，或是受到恶霸贵族的欺压，便马不停蹄地赶过去。面对来袭的兽人部落，他们会借助树林的掩护，悄无声息地靠近，接着用长弓发起凌厉攻击，利箭如雨般射向敌人，打乱其进攻节奏。而碰上那些鱼肉乡里的贵族，贝特朗也毫不畏惧，站在村民身前据理力争，若对方执意作恶，他也不惜拔剑相向，守护弱者的权益。 "/>
  		<string id="yOQMhOyU" text="农民骑士团"/>
  		<string id="mTZPbh3d" text="著名的温弗利特的格格是有史以来唯一一位被授予骑士身份，并有幸饮用圣杯之水的农民。他与他的农民骑士们一同在巴托尼亚四处游历，旨在清除这片土地上的所有邪恶。格格出身贫寒，在田间地头长大，整日与农具为伴。可命运的转折突如其来，凭借非凡的勇气与质朴的正义感，他赢得了一次改写命运的机遇，获封骑士。自此，他扔掉了锄头，换上了闪亮的铠甲，手握长剑，召集起一群志同道合的农民伙伴。这些昔日的庄稼汉，摇身一变成为勇猛无畏的骑士，跟随着格格，在巴托尼亚的乡野小道、深山古堡间穿梭。无论是烧杀抢掠的绿皮兽人，还是为非作歹的邪恶骑士，只要碰上，他们便会毫不犹豫地冲锋陷阵，以守护平民、净化土地为使命，书写着属于农民骑士的传奇。 "/>
  		
		<!-- Dogs Of War factions -->
  		<string id="XdxTeYoG" text="布拉甘萨的围城者"/>
  		<string id="1xqYYSrx" text="由卢卡·布拉干萨率领的布拉干萨围城者，是一支著名的战犬佣兵团，他们来自提利尔城邦米拉格利亚诺，接受的训练以及日常定位，都是重装弩手。这些佣兵身着厚重的板甲，甲胄上刻着米拉格利亚诺的徽记，彰显着他们的出身。手中的重型弩弓是夺命利器，经过精心打磨与调试，张力十足。平日里，卢卡·布拉干萨会督促团员刻苦训练，从装填弩箭的速度，到精准射击的技巧，无一不练。当战火燃起，他们列阵前行，沉重的步伐震得大地微微颤抖。待到进入射程，一排排弩箭呼啸而出，势大力沉，能轻易穿透敌人的盾牌与铠甲，为雇主在战场上撕开一道道血腥的口子，也为自己挣得丰厚的报酬与响亮的名声。 "/>
		<string id="d1ag2umg" text="咒缚军团"/>
  		<string id="nSuWhXri" text="被诅咒的里希特·克鲁格战团是一支古老的不死者雇佣兵部队，传言称，那些倒在他们致命刀剑下的人，都会被永远奴役。里希特·克鲁格的战斗口号早已被旧世界的人们遗忘。当这支被诅咒的部队行军穿越大地奔赴战场时，坟墓般的死寂笼罩着他们，伴随他们的唯有老旧皮革的嘎吱声与生锈金属的刮擦声。在昏暗的月色下，这支阴森的队伍缓缓前行，骷髅战士们眼眶中幽绿的火苗微微跳动，腐朽的身躯上还挂着几缕破布，手中锈迹斑斑的刀剑却依旧散发着寒光。僵尸们拖着沉重迟缓的步子，肢体不时脱落，又被麻木地捡起。而里希特·克鲁格，这个神秘又可怖的首领，骑在一匹骷髅战马上，身披残破的黑袍，散发着令人胆寒的气息，驱使着这支不死军团，去为出价最高的雇主带来毁灭与死亡。 "/>
  		<string id="WCF8XOhF" text="利奥波德的“豹团”"/>
  		<string id="TKRZXHvC" text="利奥波德的豹团是一支著名的战犬佣兵团，起源于伟大的卢奇尼城邦。豹团得名于卢奇尼传奇的豹子，它是这座城市的徽章与吉祥物。据说，这头豹子曾是城市的创立者、神圣双胞胎卢坎与卢奇尼的守护者。豹团的佣兵们无比珍视这份传承，他们将豹子的形象骄傲地绘制在盾牌、旗帜之上。士兵们身着统一的制服，以橘黑相间的色调为主，模仿豹子的斑纹，在战场上醒目又威风。每逢出征，他们士气高昂，深信那守护过城市奠基者的神秘豹子之力庇佑着自己。作战时，他们行动敏捷、战术多变，宛如丛林中的猎豹，或突袭侧翼，或包抄敌后，为雇主带来一场场胜利，在雇佣军的世界里打响了名号。 "/>
  		<string id="hDjltrNC" text="佛朗德的猎手团"/>
  		<string id="uhnNA0a3" text="沃兰德的猎骑兵团是一支赫赫有名的战犬佣兵团，他们作为全提利尔最出色骑兵的声誉，甚至超过了帝国的资深骑士，有人还说，比巴托尼亚本国的骑士还要厉害。这伙由叛教者、流亡者，以及那些被贵族和领主们扫地出门的子嗣组成的队伍，都是骑兵专家，而且和团里的每个人一样，他们的首领也是一位极为出色的骑手。沃兰德的猎骑兵团成员，各个身姿矫健，骑术精湛。他们跨下骏马皆是精挑细选，马蹄轻快又有力，鬃毛随风飘动。骑手们身着轻便却坚韧的皮甲，既能灵活作战，又能抵御一定伤害。他们手持锋利的骑枪，枪尖在阳光下闪烁寒光，腰间还别着长剑与短斧，用于近战搏斗。作战时，他们宛如一阵黑色旋风席卷而来，骑枪平举向前，精准刺向敌人的要害；一旦冲入敌阵，便迅速抽出近战武器，左右劈砍，杀得敌军人仰马翻，用一次次冲锋和无畏的战斗，捍卫着自己顶尖骑兵的名号。 "/>
  		<string id="kNxFoeAe" text="米拉格连诺的神射手"/>
  		<string id="gQz1HCnQ" text="米拉格利亚诺的神射手团是一支著名的战犬佣兵团，顾名思义，他们来自提利尔城邦米拉格利亚诺。虽说在提利尔，将弩弓用作战争武器并不罕见，但极少有雇佣兵团队能与这些神射手的精准度相媲美。这支佣兵团的成员皆是百里挑一的好手，他们自小就开始练习使用弩弓，经年累月的训练让他们对武器的操控炉火纯青。每位神射手都配有一把精心调校的特制弩弓，弩身由坚韧又轻盈的木材与金属打造，弦线紧绷有力。他们眼力极佳，能在远距离就锁定目标，无论是敌军将领的身影，还是隐藏在掩体后的弓弩手，都逃不过他们的视线。作战时，他们会巧妙地寻找掩护，或藏身于城墙垛口，或隐匿于树林之中，接着悄无声息地装填弩箭，随后只需轻轻一扣扳机，弩箭便如流星般疾射而出，精准命中目标，给敌人带来致命打击，让雇主在战场上占尽先机。 "/>
  		<string id="JIyXior4" text="里科的共和国守卫"/>
  		<string id="94fLJbuu" text="里科的共和卫队是一支著名的战犬佣兵团，来自伟大的共和制城邦雷马斯。共和卫队是在雷马斯由一群叛逆的商人组建起来的，彼时，城邦正处于共和国诞生前的艰难时期，饥荒肆虐，民众的反抗此起彼伏。这些商人不满旧有的统治秩序，决心拉起一支属于自己的武装力量。他们招募了城中那些身强体壮、渴望改变命运的青年，用从海外贸易中积攒的财富购置装备。共和卫队的成员身着统一的制服，以象征共和的蓝白为主色调，头戴饰有羽毛的头盔，显得英姿飒爽。他们手持长枪与盾牌，既能组成坚不可摧的盾墙抵御敌人冲击，又能在合适时机发起凌厉冲锋。每逢战斗，他们为了心中的共和理想、为了雇主的诉求，奋勇向前，纪律严明地执行每一项战术，逐渐在雇佣兵的世界闯出了赫赫威名。 "/>
  		<string id="k97JEMjP" text="穆赫塔尔的沙漠之犬"/>
  		<string id="U15I6Lck" text="阿尔·穆克塔尔的沙漠犬佣兵团是一支声名远扬的战犬雇佣兵队伍，来自广袤阿拉伯的干旱沙漠地区。这伙由强盗和雇佣兵组成的团伙是经验丰富的劫掠者与游击兵，他们常常骑着马，身着轻便铠甲或者皮甲，以便在攻击时行动敏捷，洗劫那些孤立的村庄和商队。沙漠犬的成员个个面容沧桑，被烈日晒得黝黑，眼神中透着狡黠与凶狠。他们胯下的马匹适应了沙漠环境，耐力非凡，马蹄踏在滚烫沙地也不见疲态。作战时，他们先是借着沙丘起伏隐藏行踪，悄无声息地靠近目标。待时机成熟，便如鬼魅般杀出，扬起漫天沙尘。骑手们挥舞着弯刀，呼喊着令人胆寒的战吼，弯刀在阳光下闪过寒光，瞬间切入商队护卫的防线，或是冲进村庄，抢夺财物、粮食，得手后又迅速消失在茫茫沙漠之中，只留下一片混乱与哭喊声。 "/>

		<!-- Named chaos cults -->
  		<string id="Qoojx8lR" text="破碎之轮密教"/>
  		<string id="CzzUlvnN" text="破碎之轮密教的信徒多年来一直在暗中秘密行事，长期图谋搞垮帝国魔法学院。作为奸奇——这位掌管魔法与禁忌知识的混沌之神的崇拜者，破碎之轮的邪教徒认为，八大魔法学院的施法方式是对魔法技艺的背叛，因为学院只会构建并管控魔法之风，却不懂得沉醉于他们黑暗技艺那混沌、狂野的本质。在帝国繁华的城镇中，这些邪教徒隐匿身形，伪装成普通市民，暗中策划着阴谋。他们趁着夜色，在废弃的地窖、阴森的小巷碰头，用晦涩难懂的语言交流着破坏计划。有人偷偷潜入学院图书馆，篡改魔法古籍，试图植入混沌思想；还有人在学院招募新学员时，蛊惑那些懵懂的年轻人，向他们宣扬混沌魔法的“自由”与“强大”，试图从内部瓦解学院的根基，好让奸奇的黑暗力量在帝国肆意蔓延。 "/>
  		<string id="hJZosXin" text="光照会"/>
  		<string id="rQCBle4E" text="光照会是一个地下兄弟会组织，表面上声称是为了成员的福祉以及助力他们的生活与事业发展。然而，这个汇聚了政界与艺术界诸多权势人物的教派，却犯下了崇拜混沌邪神奸奇与色孽的滔天恶行。该邪教有着明确的目标：权力、金钱与名声。核心圈子里的每个人在日常生活中都为帝国公众所熟知，但大部分普通成员并不知道核心成员究竟是谁。许多成员借助邪教的阴谋手段在帝国内崭露头角，而那些公然反对它的人往往都性命不保。在这个邪教兄弟会中，既有满怀野心之人，也有名人雅士，还有声名狼藉之辈，他们来自政界与艺术界，齐心协力提升彼此的知名度，延续邪教的“传统” 。 "/>
  		<string id="Of5uHFR7" text="第二血肉兄弟会"/>
  		<string id="VTMDULSm" text="崇拜纳垢的最具影响力的混沌邪教之一，便是“次生血肉兄弟会”。这个秘密组织图谋让帝国陷入污秽与疫病的泥沼，为世界最终陷入混沌的终末之时做准备。兄弟会由一群贵族组成，他们秘密集会，在阿尔道夫一座麻风病院下方的下水道里的隐秘神庙中敬拜纳垢。该邪教相信，当终末之时来临，瘟疫之主将用不朽的瘟疫搬运工的血肉，为他们每个人重塑身躯，他们把这一事件称作“蜕变” 。 "/>

  </strings>
</base>